bufu/__init__.py
bufu/bufu.py
bufu-0.0.4.dist-info/LICENSE
bufu-0.0.4.dist-info/METADATA
bufu-0.0.4.dist-info/WHEEL
bufu-0.0.4.dist-info/entry_points.txt
bufu-0.0.4.dist-info/top_level.txt
bufu-0.0.4.dist-info/RECORD
