Metadata-Version: 2.1
Name: bufu
Version: 0.0.4
Summary: Minimal file uploader CLI for Snowflake internal stage
Home-page: https://github.com/indigo13love/bufu
Author: indigo13love
Author-email: indigo13love@gmail.com
License: UNKNOWN
Platform: UNKNOWN
Classifier: Programming Language :: Python :: 3.6
Classifier: Programming Language :: Python :: 3.7
Classifier: Programming Language :: Python :: 3.8
Classifier: Operating System :: OS Independent
Requires-Python: >=3.6,<3.9
Requires-Dist: snowflake-connector-python (>=2.3.6)
Requires-Dist: fire (>=0.3.1)
